simperium/__init__.py
simperium/changes.py
simperium/core.py
simperium/optfunc.py
simperium/test/__init__.py
simperium/test/test_core.py
Simperium3-0.1.5.dist-info/LICENSE
Simperium3-0.1.5.dist-info/METADATA
Simperium3-0.1.5.dist-info/WHEEL
Simperium3-0.1.5.dist-info/top_level.txt
Simperium3-0.1.5.dist-info/RECORD
