Metadata-Version: 2.1
Name: Simperium3
Version: 0.1.5
Summary: Python 3 client for the Simperium synchronization platform
Home-page: https://git.sr.ht/~swalladge/python-simperium3
Author: Andy Gayton
Author-email: andy@simperium.com
License: UNKNOWN
Platform: UNKNOWN
Classifier: Programming Language :: Python :: 3 :: Only
Classifier: License :: OSI Approved :: MIT License
Classifier: Operating System :: OS Independent
Requires-Python: >=3
Requires-Dist: requests
